AUTHORS
ChangeLog
README.md
requirements.txt
setup.cfg
setup.py
.idea/vcs.xml
.idea/dictionaries/thuhak_zhou.xml
webtrap/__init__.py
webtrap/webtrap.py
webtrap.egg-info/PKG-INFO
webtrap.egg-info/SOURCES.txt
webtrap.egg-info/dependency_links.txt
webtrap.egg-info/entry_points.txt
webtrap.egg-info/not-zip-safe
webtrap.egg-info/pbr.json
webtrap.egg-info/requires.txt
webtrap.egg-info/top_level.txt